setup.py
Checkm.egg-info/PKG-INFO
Checkm.egg-info/SOURCES.txt
Checkm.egg-info/dependency_links.txt
Checkm.egg-info/not-zip-safe
Checkm.egg-info/top_level.txt
bin/bagitmanifest
bin/checkm
checkm/__init__.py
checkm/checkm.py