Metadata-Version: 1.0
Name: Checkm
Version: 0.4
Summary: Checkm - create reports on the checksums of sets of files or URLs resources.
Home-page: http://packages.python.org/Checkm/
Author: Ben O'Steen
Author-email: bosteen@gmail.com
License: MIT
Platform: UNKNOWN
